Metadata-Version: 1.0
Name: fund-dist
Version: 1.0
Summary: Fundamental distributions: Guassian, Binomial, Poisson
Home-page: UNKNOWN
Author: Ozan Ersoy
Author-email: ozan.ersoy+pypi@gmail.com
License: UNKNOWN
Platform: UNKNOWN
